parallel_manager/__init__.py
parallel_manager/manager.py
parallel_manager/packet.py
parallel_manager/worker.py
parallel_manager/workerGroup.py
parallel_manager-0.1.0.dist-info/LICENSE
parallel_manager-0.1.0.dist-info/METADATA
parallel_manager-0.1.0.dist-info/WHEEL
parallel_manager-0.1.0.dist-info/top_level.txt
parallel_manager-0.1.0.dist-info/RECORD
