Metadata-Version: 2.1
Name: parallel-manager
Version: 0.1.0
Summary: A simple shell command manager. Used for running parallel simulations.
Author-email: William An <china_aisa@live.com>
Project-URL: Homepage, https://github.com/William-An/parallel-manager
Project-URL: Bug Tracker, https://github.com/William-An/parallel-manager/issues
Classifier: Programming Language :: Python :: 3
Classifier: License :: OSI Approved :: MIT License
Classifier: Operating System :: OS Independent
Requires-Python: >=3.8
License-File: LICENSE
